setup.cfg
setup.py
easydate/__init__.py
easydate/easydate_class.py
easydate.egg-info/PKG-INFO
easydate.egg-info/SOURCES.txt
easydate.egg-info/dependency_links.txt
easydate.egg-info/top_level.txt