Metadata-Version: 1.1
Name: easydate
Version: 0.13
Summary: Very easy datetime manipulation and sequence generation
Home-page: https://github.com/super-seb/python_easydate
Author: SebJ
Author-email: sebj.global@gmail.com
License: UNKNOWN
Download-URL: https://github.com/super-seb/python_easydate/tarball/0.1
Keywords: date,time,sequence,week,fortnight,quarter
Platform: UNKNOWN
